{
    "id": "609473",
    "ident": "GB-1355",
    "type": "closed",
    "name": "RAF Brackla",
    "latitude_deg": "57.540555",
    "longitude_deg": "-3.913056",
    "elevation_ft": "94",
    "continent": "EU",
    "iso_country": "GB",
    "iso_region": "GB-SCT",
    "municipality": "Brackla, Highland",
    "scheduled_service": "no",
    "icao_code": "",
    "iata_code": "",
    "gps_code": "",
    "local_code": "",
    "home_link": "",
    "wikipedia_link": "https://en.wikipedia.org/wiki/RAF_Brackla",
    "keywords": "Culcharry",
    "country": {
        "id": "302688",
        "code": "GB",
        "name": "United Kingdom",
        "continent": "EU",
        "wikipedia_link": "https://en.wikipedia.org/wiki/United_Kingdom",
        "keywords": "Great Britain"
    },
    "region": {
        "id": "306377",
        "code": "GB-SCT",
        "local_code": "SCT",
        "name": "Scotland",
        "continent": "EU",
        "iso_country": "GB",
        "wikipedia_link": "https://en.wikipedia.org/wiki/Scotland",
        "keywords": "Scottish airports, Puirt-adhair Albannach"
    }
}