{
    "id": "605924",
    "ident": "IR-0233",
    "type": "heliport",
    "name": "Khosravi Border Patrol Heliport",
    "latitude_deg": "34.39121",
    "longitude_deg": "45.47892",
    "elevation_ft": "886",
    "continent": "AS",
    "iso_country": "IR",
    "iso_region": "IR-05",
    "municipality": "Khosravi",
    "scheduled_service": "no",
    "icao_code": "",
    "iata_code": "",
    "gps_code": "",
    "local_code": "",
    "home_link": "",
    "wikipedia_link": "",
    "keywords": "",
    "country": {
        "id": "302637",
        "code": "IR",
        "name": "Iran",
        "continent": "AS",
        "wikipedia_link": "https://en.wikipedia.org/wiki/Iran",
        "keywords": "فرودگاه های ایران"
    },
    "region": {
        "id": "304234",
        "code": "IR-05",
        "local_code": "05",
        "name": "Kermanshah Province",
        "continent": "AS",
        "iso_country": "IR",
        "wikipedia_link": "https://en.wikipedia.org/wiki/Kermanshah_Province",
        "keywords": "Airports in Kermanshah Province"
    }
}